{
    "custom_classes": 0,
    "images": [
        {
            "classifiers": [
                {
                    "classes": [
                        {
                            "class": "guitar",
                            "score": 0.903,
                            "type_hierarchy": "/musical instrument/stringed instrument/guitar"
                        },
                        {
                            "class": "stringed instrument",
                            "score": 0.92
                        },
                        {
                            "class": "musical instrument",
                            "score": 0.977
                        },
                        {
                            "class": "bass guitar",
                            "score": 0.613,
                            "type_hierarchy": "/musical instrument/bass (musical instrument)/bass guitar"
                        },
                        {
                            "class": "bass (musical instrument)",
                            "score": 0.671
                        },
                        {
                            "class": "electric guitar",
                            "score": 0.532,
                            "type_hierarchy": "/musical instrument/stringed instrument/guitar/electric guitar"
                        },
                        {
                            "class": "reddish brown color",
                            "score": 0.984
                        }
                    ],
                    "classifier_id": "default",
                    "name": "default"
                }
            ],
            "image": "input_images\\guitar_image_0036.jpg"
        }
    ],
    "images_processed": 1,
    "response_time": 2.1177265644073486
}