{
    "custom_classes": 0,
    "images": [
        {
            "classifiers": [
                {
                    "classes": [
                        {
                            "class": "limpkin (wading bird)",
                            "score": 0.937,
                            "type_hierarchy": "/animal/bird/aquatic bird/limpkin (wading bird)"
                        },
                        {
                            "class": "aquatic bird",
                            "score": 0.989
                        },
                        {
                            "class": "bird",
                            "score": 0.989
                        },
                        {
                            "class": "animal",
                            "score": 0.989
                        },
                        {
                            "class": "courlan (wading bird)",
                            "score": 0.754,
                            "type_hierarchy": "/animal/bird/aquatic bird/courlan (wading bird)"
                        },
                        {
                            "class": "sea green color",
                            "score": 0.704
                        }
                    ],
                    "classifier_id": "default",
                    "name": "default"
                }
            ],
            "image": "input_images\\ibis_image_0065.jpg"
        }
    ],
    "images_processed": 1,
    "response_time": 1.1370759010314941
}